azure/mgmt/storageimportexport/__init__.py
azure/mgmt/storageimportexport/_configuration.py
azure/mgmt/storageimportexport/_storage_import_export.py
azure/mgmt/storageimportexport/version.py
azure/mgmt/storageimportexport/models/__init__.py
azure/mgmt/storageimportexport/models/_models.py
azure/mgmt/storageimportexport/models/_models_py3.py
azure/mgmt/storageimportexport/models/_paged_models.py
azure/mgmt/storageimportexport/models/_storage_import_export_enums.py
azure/mgmt/storageimportexport/operations/__init__.py
azure/mgmt/storageimportexport/operations/_bit_locker_keys_operations.py
azure/mgmt/storageimportexport/operations/_jobs_operations.py
azure/mgmt/storageimportexport/operations/_locations_operations.py
azure/mgmt/storageimportexport/operations/_operations.py
azure_mgmt_storageimportexport-0.1.0.dist-info/METADATA
azure_mgmt_storageimportexport-0.1.0.dist-info/WHEEL
azure_mgmt_storageimportexport-0.1.0.dist-info/top_level.txt
azure_mgmt_storageimportexport-0.1.0.dist-info/RECORD
